bldlib
