Metadata-Version: 2.1
Name: bld
Version: 0.8.1
Summary: Bld project build helper
Home-page: https://github.com/osechet/bld
Author: Olivier Sechet
Author-email: osechet@gmail.com
License: MIT
Keywords: build,project,developer,tool
Platform: UNKNOWN
Classifier: Development Status :: 3 - Alpha
Classifier: Intended Audience :: Developers
Classifier: Topic :: Software Development :: Build Tools
Classifier: License :: OSI Approved :: MIT License
Classifier: Programming Language :: Python :: 3
Classifier: Programming Language :: Python :: 3.5
Classifier: Programming Language :: Python :: 3.6
Classifier: Programming Language :: Python :: 3.7
Classifier: Programming Language :: Python :: 3.8
Classifier: Programming Language :: Python :: 3 :: Only
Provides-Extra: test
Provides-Extra: dev
